html2css.py
html2css-1.0.2.dist-info/METADATA
html2css-1.0.2.dist-info/WHEEL
html2css-1.0.2.dist-info/entry_points.txt
html2css-1.0.2.dist-info/top_level.txt
html2css-1.0.2.dist-info/RECORD
