Metadata-Version: 2.4
Name: html2css
Version: 1.0.2
Summary: A simple CLI tool to generate CSS skeleton from HTML
Home-page: https://github.com/yourusername/html2css
Author: Your Name
Author-email: your@email.com
Classifier: Programming Language :: Python :: 3
Classifier: License :: OSI Approved :: MIT License
Classifier: Operating System :: OS Independent
Requires-Python: >=3.6
Dynamic: author
Dynamic: author-email
Dynamic: classifier
Dynamic: description
Dynamic: description-content-type
Dynamic: home-page
Dynamic: requires-python
Dynamic: summary
